{
  "cli": {
    "version": ">= 7.0.0"
  },
  "build": {
    "development": {
      "developmentClient": true,
      "distribution": "internal",
      "env": {
        "EXPO_PUBLIC_API_URL": "http://localhost:3002",
        "EXPO_PUBLIC_ENV": "development"
      }
    },
    "preview": {
      "distribution": "internal",
      "ios": {
        "simulator": false
      },
      "android": {
        "buildType": "apk"
      },
      "env": {
        "EXPO_PUBLIC_API_URL": "https://api.actguidance.app",
        "EXPO_PUBLIC_ENV": "staging"
      }
    },
    "production": {
      "env": {
        "EXPO_PUBLIC_API_URL": "https://api.actguidance.app",
        "EXPO_PUBLIC_ENV": "production"
      }
    }
  },
  "submit": {
    "production": {
      "ios": {},
      "android": {
        "serviceAccountKeyPath": "./google-service-account.json",
        "track": "production"
      }
    }
  }
}
